mtv_dl/__init__.py
mtv_dl/mtv_dl.py
mtv_dl-0.27.3.dist-info/WHEEL
mtv_dl-0.27.3.dist-info/entry_points.txt
mtv_dl-0.27.3.dist-info/METADATA
mtv_dl-0.27.3.dist-info/RECORD
