Metadata-Version: 2.3
Name: mtv_dl
Version: 0.27.3
Summary: MediathekView Downloader
Author: Frank Epperlein
Author-email: Frank Epperlein <frank+mtv_dl@epperle.in>
License: MIT License
Classifier: Topic :: Multimedia :: Video
Classifier: Development Status :: 4 - Beta
Classifier: Environment :: Console
Classifier: License :: Public Domain
Classifier: Programming Language :: Python :: 3.10
Classifier: License :: OSI Approved :: MIT License
Requires-Dist: iso8601~=2.1.0
Requires-Dist: durationpy~=0.10
Requires-Dist: pyyaml~=6.0
Requires-Dist: beautifulsoup4~=4.13.4
Requires-Dist: rich~=14.0.0
Requires-Dist: certifi~=2025.4.26
Requires-Dist: ijson~=3.4.0
Requires-Dist: typer~=0.16.0
Requires-Dist: typer-config[yaml]~=1.4.2
Requires-Python: >=3.10
